PolynomialCalculator/polynomial.vhd
library IEEE;

use IEEE.std_logic_1164.all;
use ieee.numeric_std.all;

entity polynomial is
	port(
		i_clk: in std_logic;
		i_reset: in std_logic;
		i_x: in signed(7 downto 0);
		i_coeffients: in std_logic_vector(8*8-1 downto 0);
		o_ready : out std_logic;
		o_y: out signed(31 downto 0)
	    );
end polynomial;

architecture rtl of polynomial is

	signal cntrl: integer range 0 to 7 := 0;
	signal stage_result: signed(31 downto 0) := X"00000000";
	signal ready: std_logic := '0';

begin
	
	process(i_clk) 
	begin
		if i_reset = '1' then

			cntrl <= 0;
			stage_result <= X"00000000";
			ready <= '0';
			o_y <= (others => '0');

		elsif rising_edge(i_clk) then

			if ready = '0' then

				if cntrl = 0 then
					stage_result <= (stage_result'range => '0') + signed(i_coeffients(7 downto 0)) * i_x;
				else
					-- stage_result <= signed(i_coeffients(8*cntrl+7 downto 8*cntrl)) + stage_result * i_x;
					stage_result <= (stage_result'range => '0') + stage_result;
				end if;

				if cntrl = 7 then -- Manage overflow
					cntrl <= 0;
					ready <= '1';
					o_y <= stage_result;
				else
					cntrl <= cntrl + 1;
				end if;

			end if;

		end if;
	end process;

	o_ready <= ready;

end architecture;

PolynomialCalculator/polynomial_tb.vhd
library IEEE;

use IEEE.std_logic_1164.all;
use IEEE.numeric_std.all;

entity polynomial_tb is
end polynomial_tb;

architecture rtl of polynomial_tb is

	component polynomial
	port(
		i_clk: in std_logic;
		i_reset: in std_logic;
		i_x: in signed(7 downto 0);
		i_coeffients: in std_logic_vector(8*8-1 downto 0);
		o_ready : out std_logic;
		o_y: out signed(31 downto 0)
	    );
	end component polynomial;

	constant CLK_PERIOD : time := 5 ns;

	signal i_clk, i_reset : std_logic := '0';
	signal i_coeffients: std_logic_vector(8*8-1 downto 0);

	signal o_ready: std_logic;
	signal o_y: signed(31 downto 0);

	-- Define your polynomial here
	type t_coeffients is array(0 to 7) of signed(7 downto 0);
	signal coeffients: t_coeffients := (X"00", X"00", X"00", X"00", X"00", X"01", X"02", X"03");
	signal i_x: signed(7 downto 0) := X"00";

begin

	uut : polynomial
	port map(
		i_clk => i_clk,
		i_reset => i_reset,
		i_x => i_x,
		i_coeffients => i_coeffients,
		o_ready => o_ready,
		o_y => o_y
	);

	-- Assign co-effients
	gen_coeff: for i in 0 to 7 generate
		i_coeffients(8*i+7 downto 8*i) <= std_logic_vector(coeffients(i));
	end generate gen_coeff;

	clk_proc: process
	begin
		wait for CLK_PERIOD/2;
		i_clk <= not i_clk;
	end process;

	stim_proc: process
	begin
		i_reset <= '1';
		wait for 10 ns;
		i_reset <= '0';
		wait;
	end process;
end rtl;

PolynomialCalculator/polynomial_tb.vcd
$date
  Fri Oct  1 16:47:17 2021
$end
$version
  GHDL v0
$end
$timescale
  1 fs
$end
$scope module standard $end
$upscope $end
$scope module std_logic_1164 $end
$upscope $end
$scope module numeric_std $end
$upscope $end
$scope module polynomial_tb $end
$var reg 1 ! i_clk $end
$var reg 1 " i_reset $end
$var reg 64 # i_coeffients[63:0] $end
$var reg 1 $ o_ready $end
$var reg 32 % o_y[31:0] $end
$var  & coeffients $end
$var reg 8 ' i_x[7:0] $end
$scope module uut $end
$var reg 1 ( i_clk $end
$var reg 1 ) i_reset $end
$var reg 8 * i_x[7:0] $end
$var reg 64 + i_coeffients[63:0] $end
$var reg 1 , o_ready $end
$var reg 32 - o_y[31:0] $end
$var integer 32 . cntrl $end
$var reg 32 / stage_result[31:0] $end
$var reg 1 0 ready $end
$upscope $end
$scope module gen_coeff(0) $end
$upscope $end
$scope module gen_coeff(1) $end
$upscope $end
$scope module gen_coeff(2) $end
$upscope $end
$scope module gen_coeff(3) $end
$upscope $end
$scope module gen_coeff(4) $end
$upscope $end
$scope module gen_coeff(5) $end
$upscope $end
$scope module gen_coeff(6) $end
$upscope $end
$scope module gen_coeff(7) $end
$upscope $end
$upscope $end
$enddefinitions $end
#0
0!
1"
b0000001100000010000000010000000000000000000000000000000000000000 #
0$
bUUUUUUUUUUUUUUUUUUUUUUUUUUUUUUUU %
&
b00000000 '
0(
1)
b00000000 *
b0000001100000010000000010000000000000000000000000000000000000000 +
0,
bUUUUUUUUUUUUUUUUUUUUUUUUUUUUUUUU -
b0 .
b00000000000000000000000000000000 /
00
#2500000
1!
b00000000000000000000000000000000 %
1(
b00000000000000000000000000000000 -
#5000000
0!
0(
#7500000
1!
1(
#10000000
0!
0"
0(
0)
#12500000
1!
1(
b1 .
#15000000
0!
0(
#17500000
1!
1(
b10 .
#20000000
0!
0(
#22500000
1!
1(
b11 .
#25000000
0!
0(
#27500000
1!
1(
b100 .
#30000000
0!
0(
#32500000
1!
1(
b101 .
#35000000
0!
0(
#37500000
1!
1(
b110 .
#40000000
0!
0(
#42500000
1!
1(
b111 .
#45000000
0!
0(
#47500000
1!
1$
1(
1,
b0 .
10
