FIFO/fifo.vhd
library IEEE;

use IEEE.std_logic_1164.all;
use IEEE.numeric_std.all;

entity fifo is
	
	Generic(g_WIDTH : integer := 8;
					g_DEPTH : integer := 1);
	Port(
			reset: in std_logic;
			wr_clk: in std_logic;
			i_data_wr: in unsigned(g_WIDTH-1 downto 0);
			i_write_en: in std_logic;
			o_full: out std_logic;

			rd_clk: in std_logic;
			o_data_rd: out unsigned(g_WIDTH-1 downto 0);
			i_read_en: in std_logic;
			o_empty: out std_logic);

end fifo;

architecture arch of fifo is

	type t_FIFO is array (0 to g_DEPTH-1) of unsigned(g_WIDTH-1 downto 0);
	signal fifo : t_FIFO := (others => (others => '0'));

	signal fifo_wr_index: integer range 0 to g_DEPTH-1 := 0;
	signal fifo_full: std_logic := '0';
	signal fifo_rd_index: integer range 0 to g_DEPTH-1 := 0;
	signal fifo_empty: std_logic := '1';

begin 

	-- Async assignments
	o_data_rd <= fifo(fifo_rd_index);
	o_full <= fifo_full;
	o_empty <= fifo_empty;

	write_proc: process(wr_clk) is
	begin
		if rising_edge(wr_clk) then

			-- Write to FIFO
			if (i_write_en = '1') then 
				fifo(fifo_wr_index) <= i_data_wr;
				if (fifo_empty = '1') then
					fifo_empty <= '0';
				end if;
			end if;

			-- Update write index
			-- Cannot write if FIFO is full
			if (i_write_en = '1' and fifo_full = '0') then
				if (fifo_wr_index = g_DEPTH-1) then
					fifo_wr_index <= 0;
					fifo_full <= '1';
				else
					fifo_wr_index <= fifo_wr_index + 1;
				end if;
			end if;

		end if;
	end process;


	read_proc: process(rd_clk) is
	begin
		if rising_edge(rd_clk) then

			-- Update read index
			-- Cannot read if FIFO is empty
			if (i_read_en = '1' and fifo_empty = '0') then
				if (fifo_rd_index = g_WIDTH-1) then
					fifo_rd_index <= 0;
				else
					fifo_rd_index <= fifo_rd_index + 1;
				end if;
			end if;

		end if;
	end process;

end arch;

FIFO/fifo_tb.vhd
library IEEE;

use IEEE.std_logic_1164.all;
use IEEE.numeric_std.all;

entity fifo_tb is
end fifo_tb;

architecture arch of fifo_tb is

	component fifo is
		Generic(g_WIDTH : integer := 8;
						g_DEPTH : integer := 1);
		Port(
				 reset: in std_logic;
				 wr_clk: in std_logic;
				 i_data_wr: in unsigned(g_WIDTH-1 downto 0);
				 i_write_en: in std_logic;
				 o_full: out std_logic;
				 rd_clk: in std_logic;
				 o_data_rd: out unsigned(g_WIDTH-1 downto 0);
				 i_read_en: in std_logic;
				 o_empty: out std_logic);
	end component;

	constant WR_CLK_PERIOD: time := 1 ns;
	constant RD_CLK_PERIOD: time := 2 ns;
	signal wr_clk, rd_clk: std_logic := '0';
	signal reset: std_logic := '0';

	signal i_data_wr: unsigned(7 downto 0) := X"05";
	signal o_data_rd: unsigned(7 downto 0);
	signal i_write_en, i_read_en: std_logic := '0';
	signal o_full, o_empty: std_logic;


begin

	fifo_inst: fifo
	generic map(g_WIDTH => 8,
	g_DEPTH => 8)
	port map(
	reset=>reset,
	wr_clk=>wr_clk,
	i_data_wr=>i_data_wr,
	i_write_en=>i_write_en,
	o_full=>o_full,

	rd_clk=>rd_clk,
	o_data_rd=>o_data_rd,
	i_read_en=>i_read_en,
	o_empty=>o_empty
	);

	wr_clk_proc: process
	begin
		wait for WR_CLK_PERIOD/2;
		wr_clk <= not wr_clk;
	end process;

	rd_clk_proc: process
	begin
		wait for RD_CLK_PERIOD/2;
		rd_clk <= not rd_clk;
	end process;


	write_proc: process(wr_clk)
	begin

		if rising_edge(wr_clk) then
			if not (o_full = '1') then 
				i_write_en <= '1';
				i_data_wr <= i_data_wr + 1;
			end if;	
		end if;

	end process;

	read_proc: process
	begin
		-- Wait arbitary long time and start reading FIFO
		wait for 3 ns;
		i_read_en <= '1';
	end process;


end arch;

FIFO/fifo_tb.vcd
$date
  Fri Sep 24 14:06:25 2021
$end
$version
  GHDL v0
$end
$timescale
  1 fs
$end
$scope module standard $end
$upscope $end
$scope module std_logic_1164 $end
$upscope $end
$scope module numeric_std $end
$upscope $end
$scope module fifo_tb $end
$var reg 1 ! wr_clk $end
$var reg 1 " rd_clk $end
$var reg 1 # reset $end
$var reg 8 $ i_data_wr[7:0] $end
$var reg 8 % o_data_rd[7:0] $end
$var reg 1 & i_write_en $end
$var reg 1 ' i_read_en $end
$var reg 1 ( o_full $end
$var reg 1 ) o_empty $end
$scope module fifo_inst $end
$var reg 1 * reset $end
$var reg 1 + wr_clk $end
$var reg 8 , i_data_wr[7:0] $end
$var reg 1 - i_write_en $end
$var reg 1 . o_full $end
$var reg 1 / rd_clk $end
$var reg 8 0 o_data_rd[7:0] $end
$var reg 1 1 i_read_en $end
$var reg 1 2 o_empty $end
$var  3 fifo $end
$var integer 32 4 fifo_wr_index $end
$var reg 1 5 fifo_full $end
$var integer 32 6 fifo_rd_index $end
$var reg 1 7 fifo_empty $end
$upscope $end
$upscope $end
$enddefinitions $end
#0
0!
0"
0#
b00000101 $
b00000000 %
0&
0'
0(
1)
0*
0+
b00000101 ,
0-
0.
0/
b00000000 0
01
12
3
b0 4
05
b0 6
17
#500000
1!
b00000110 $
1&
1+
b00000110 ,
1-
#1000000
0!
1"
0+
1/
#1500000
1!
b00000111 $
b00000110 %
0)
1+
b00000111 ,
b00000110 0
02
b1 4
07
#2000000
0!
0"
0+
0/
#2500000
1!
b00001000 $
1+
b00001000 ,
b10 4
#3000000
0!
1"
b00000111 %
1'
0+
1/
b00000111 0
11
b1 6
#3500000
1!
b00001001 $
1+
b00001001 ,
b11 4
#4000000
0!
0"
0+
0/
#4500000
1!
b00001010 $
1+
b00001010 ,
b100 4
#5000000
0!
1"
b00001000 %
0+
1/
b00001000 0
b10 6
#5500000
1!
b00001011 $
1+
b00001011 ,
b101 4
#6000000
0!
0"
0+
0/
#6500000
1!
b00001100 $
1+
b00001100 ,
b110 4
#7000000
0!
1"
b00001001 %
0+
1/
b00001001 0
b11 6
#7500000
1!
b00001101 $
1+
b00001101 ,
b111 4
#8000000
0!
0"
0+
0/
#8500000
1!
b00001110 $
1(
1+
b00001110 ,
1.
b0 4
15
#9000000
0!
1"
b00001010 %
0+
1/
b00001010 0
b100 6
#9500000
1!
1+
#10000000
0!
0"
0+
0/
#10500000
1!
1+
#11000000
0!
1"
b00001011 %
0+
1/
b00001011 0
b101 6
#11500000
1!
1+
#12000000
0!
0"
0+
0/
#12500000
1!
1+
#13000000
0!
1"
b00001100 %
0+
1/
b00001100 0
b110 6
#13500000
1!
1+
#14000000
0!
0"
0+
0/
#14500000
1!
1+
#15000000
0!
1"
b00001101 %
0+
1/
b00001101 0
b111 6
#15500000
1!
1+
#16000000
0!
0"
0+
0/
#16500000
1!
1+
#17000000
0!
1"
b00001110 %
0+
1/
b00001110 0
b0 6
#17500000
1!
1+
#18000000
0!
0"
0+
0/
#18500000
1!
1+
#19000000
0!
1"
b00000111 %
0+
1/
b00000111 0
b1 6
#19500000
1!
1+
#20000000
0!
0"
0+
0/
#20500000
1!
1+
#21000000
0!
1"
b00001000 %
0+
1/
b00001000 0
b10 6
#21500000
1!
1+
#22000000
0!
0"
0+
0/
#22500000
1!
1+
#23000000
0!
1"
b00001001 %
0+
1/
b00001001 0
b11 6
#23500000
1!
1+
#24000000
0!
0"
0+
0/
#24500000
1!
1+
#25000000
0!
1"
b00001010 %
0+
1/
b00001010 0
b100 6
#25500000
1!
1+
#26000000
0!
0"
0+
0/
#26500000
1!
1+
#27000000
0!
1"
b00001011 %
0+
1/
b00001011 0
b101 6
#27500000
1!
1+
#28000000
0!
0"
0+
0/
#28500000
1!
1+
#29000000
0!
1"
b00001100 %
0+
1/
b00001100 0
b110 6
#29500000
1!
1+
#30000000
0!
0"
0+
0/
#30500000
1!
1+
#31000000
0!
1"
b00001101 %
0+
1/
b00001101 0
b111 6
#31500000
1!
1+
#32000000
0!
0"
0+
0/
#32500000
1!
1+
#33000000
0!
1"
b00001110 %
0+
1/
b00001110 0
b0 6
#33500000
1!
1+
#34000000
0!
0"
0+
0/
#34500000
1!
1+
#35000000
0!
1"
b00000111 %
0+
1/
b00000111 0
b1 6
#35500000
1!
1+
#36000000
0!
0"
0+
0/
#36500000
1!
1+
#37000000
0!
1"
b00001000 %
0+
1/
b00001000 0
b10 6
#37500000
1!
1+
#38000000
0!
0"
0+
0/
#38500000
1!
1+
#39000000
0!
1"
b00001001 %
0+
1/
b00001001 0
b11 6
#39500000
1!
1+
#40000000
0!
0"
0+
0/
#40500000
1!
1+
#41000000
0!
1"
b00001010 %
0+
1/
b00001010 0
b100 6
#41500000
1!
1+
#42000000
0!
0"
0+
0/
#42500000
1!
1+
#43000000
0!
1"
b00001011 %
0+
1/
b00001011 0
b101 6
#43500000
1!
1+
#44000000
0!
0"
0+
0/
#44500000
1!
1+
#45000000
0!
1"
b00001100 %
0+
1/
b00001100 0
b110 6
#45500000
1!
1+
#46000000
0!
0"
0+
0/
#46500000
1!
1+
#47000000
0!
1"
b00001101 %
0+
1/
b00001101 0
b111 6
#47500000
1!
1+
#48000000
0!
0"
0+
0/
#48500000
1!
1+
#49000000
0!
1"
b00001110 %
0+
1/
b00001110 0
b0 6
