RandomNumberGenerator_LSFR/lsfr.vhd
library IEEE;

use ieee.std_logic_1164.all;
use ieee.numeric_std.all;

entity lsfr is
	Port(
		i_clk: in std_logic;
		i_reset: in std_logic;
		i_init: in std_logic;
		i_seed: in std_logic_vector(7 downto 0);
		o_lsfr: out std_logic_vector(7 downto 0)
	);
end lsfr;

architecture rtl of lsfr is

	signal lsfr_buf: std_logic_vector(8 downto 1) := (others => '0');

begin

	process(i_clk)
	begin
		
		-- if (i_reset = '1') then
		--	o_lsfr <= (others => '0');
		-- end if;

		if rising_edge(i_clk) then

			if (i_init = '1') then

				lsfr_buf <= i_seed;

			else
				
				lsfr_buf(8) <= lsfr_buf(7);
				lsfr_buf(7) <= lsfr_buf(6);
				lsfr_buf(6) <= lsfr_buf(5);
				lsfr_buf(5) <= lsfr_buf(4);
				lsfr_buf(4) <= lsfr_buf(3);
				lsfr_buf(3) <= lsfr_buf(2);
				lsfr_buf(2) <= lsfr_buf(1);
				lsfr_buf(1) <= lsfr_buf(8) xnor lsfr_buf(6) xnor lsfr_buf(5) xnor lsfr_buf(4);

			end if;

		end if;

	end process;

	o_lsfr <= lsfr_buf(8 downto 1);

end rtl;

RandomNumberGenerator_LSFR/lsfr_tb.vhd
library IEEE;

use ieee.std_logic_1164.all;
use ieee.numeric_std.all;

entity lsfr_tb is
end lsfr_tb;

architecture rtl of lsfr_tb is

	component lsfr is
		Port(
					i_clk: in std_logic;
					i_reset: in std_logic;
					i_init: in std_logic;
					i_seed: in std_logic_vector(7 downto 0);
					o_lsfr: out std_logic_vector(7 downto 0)
				);
	end component;

	constant CLK_PERIOD : time := 5 ns;
	constant SEED: std_logic_vector(7 downto 0) := (others => '0');
	
	signal i_clk, i_reset, i_init: std_logic := '0';
	signal o_lsfr: std_logic_vector(7 downto 0) := (others => '0');

begin

	lsfr_inst: lsfr
	Port map(
		i_clk => i_clk,
		i_reset => i_reset,
		i_init => i_init,
		i_seed => SEED,
		o_lsfr => o_lsfr
	);

	clk_proc: process
	begin
		wait for CLK_PERIOD/2;
		i_clk <= not i_clk;
	end process;

	stim_proc: process
	begin
		i_reset <= '1';
		i_init <= '1';
		wait for 2 ns;
		i_reset <= '0';
		wait for 2 ns;
		i_init <= '0';
		wait;
	end process;

end rtl;

RandomNumberGenerator_LSFR/lsfr_tb.vcd
$date
  Sat Sep 25 21:20:23 2021
$end
$version
  GHDL v0
$end
$timescale
  1 fs
$end
$scope module standard $end
$upscope $end
$scope module std_logic_1164 $end
$upscope $end
$scope module numeric_std $end
$upscope $end
$scope module lsfr_tb $end
$var reg 1 ! i_clk $end
$var reg 1 " i_reset $end
$var reg 1 # i_init $end
$var reg 8 $ o_lsfr[7:0] $end
$scope module lsfr_inst $end
$var reg 1 % i_clk $end
$var reg 1 & i_reset $end
$var reg 1 ' i_init $end
$var reg 8 ( i_seed[7:0] $end
$var reg 8 ) o_lsfr[7:0] $end
$var reg 8 * lsfr_buf[8:1] $end
$upscope $end
$upscope $end
$enddefinitions $end
#0
0!
1"
1#
b00000000 $
0%
1&
1'
b00000000 (
b00000000 )
b00000000 *
#2000000
0"
0&
#2500000
1!
1%
#4000000
0#
0'
#5000000
0!
0%
#7500000
1!
b00000001 $
1%
b00000001 )
b00000001 *
#10000000
0!
0%
#12500000
1!
b00000011 $
1%
b00000011 )
b00000011 *
#15000000
0!
0%
#17500000
1!
b00000111 $
1%
b00000111 )
b00000111 *
#20000000
0!
0%
#22500000
1!
b00001111 $
1%
b00001111 )
b00001111 *
#25000000
0!
0%
#27500000
1!
b00011110 $
1%
b00011110 )
b00011110 *
#30000000
0!
0%
#32500000
1!
b00111101 $
1%
b00111101 )
b00111101 *
#35000000
0!
0%
#37500000
1!
b01111010 $
1%
b01111010 )
b01111010 *
#40000000
0!
0%
#42500000
1!
b11110100 $
1%
b11110100 )
b11110100 *
#45000000
0!
0%
#47500000
1!
b11101000 $
1%
b11101000 )
b11101000 *
#50000000
0!
0%
#52500000
1!
b11010000 $
1%
b11010000 )
b11010000 *
#55000000
0!
0%
#57500000
1!
b10100001 $
1%
b10100001 )
b10100001 *
#60000000
0!
0%
#62500000
1!
b01000011 $
1%
b01000011 )
b01000011 *
#65000000
0!
0%
#67500000
1!
b10000111 $
1%
b10000111 )
b10000111 *
#70000000
0!
0%
#72500000
1!
b00001110 $
1%
b00001110 )
b00001110 *
#75000000
0!
0%
#77500000
1!
b00011100 $
1%
b00011100 )
b00011100 *
#80000000
0!
0%
#82500000
1!
b00111001 $
1%
b00111001 )
b00111001 *
#85000000
0!
0%
#87500000
1!
b01110010 $
1%
b01110010 )
b01110010 *
#90000000
0!
0%
#92500000
1!
b11100101 $
1%
b11100101 )
b11100101 *
#95000000
0!
0%
#97500000
1!
b11001011 $
1%
b11001011 )
b11001011 *
