Multiplexers/multiplexer.vhd
library IEEE;
use IEEE.std_logic_1164.all;
use IEEE.numeric_std.all;

entity mux is
port (
			 	i_data_0: in std_logic_vector(3 downto 0);
				i_data_1: in std_logic_vector(3 downto 0);
				i_data_2: in std_logic_vector(3 downto 0);
				i_data_3: in std_logic_vector(3 downto 0);
				s: in integer range 0 to 3;
				o_y: out std_logic_vector(3 downto 0)
			 );
end mux;

architecture arch1 of mux is

begin

	with s select
		o_y <= i_data_0 when 0,
					 i_data_1 when 1,
					 i_data_2 when 2,
					 i_data_3 when 3;

end arch1;

Multiplexers/mux_tb.vhd
library IEEE;
use IEEE.std_logic_1164.all;
use IEEE.numeric_std.all;

entity mux_tb is
end mux_tb;

architecture arch1 of mux_tb is

	component mux is
	port (i_data_0: in std_logic_vector(3 downto 0);
				i_data_1: in std_logic_vector(3 downto 0);
				i_data_2: in std_logic_vector(3 downto 0);
				i_data_3: in std_logic_vector(3 downto 0);
				s: in integer range 0 to 3;
				o_y: out std_logic_vector(3 downto 0)
	);
	end component;

	signal i_data_0, i_data_1, i_data_2, i_data_3, o_y: std_logic_vector(3 downto 0) := (others => '0');
	signal s: integer range 0 to 3 := 0;

begin

	mux_inst: mux
	port map(i_data_0 => i_data_0,
						i_data_1 => i_data_1,
						i_data_2 => i_data_2,
						i_data_3 => i_data_3,
						s => s,
						o_y => o_y
					);

	stim: process begin

		i_data_0 <= std_logic_vector(to_unsigned(2, i_data_0'length));
		i_data_1 <= std_logic_vector(to_unsigned(5, i_data_1'length));
		i_data_2 <= std_logic_vector(to_unsigned(10, i_data_2'length));
		i_data_3 <= std_logic_vector(to_unsigned(15, i_data_3'length));

		wait for 5 ns;
		s <= 1;

		wait for 5 ns;
		s <= 2;

		wait for 5 ns;
		s <= 3;

	end process;

end arch1;

Multiplexers/mux.vcd
$date
  Sun Sep 12 11:09:39 2021
$end
$version
  GHDL v0
$end
$timescale
  1 fs
$end
$scope module standard $end
$upscope $end
$scope module std_logic_1164 $end
$upscope $end
$scope module numeric_std $end
$upscope $end
$scope module mux_tb $end
$var reg 4 ! i_data_0[3:0] $end
$var reg 4 " i_data_1[3:0] $end
$var reg 4 # i_data_2[3:0] $end
$var reg 4 $ i_data_3[3:0] $end
$var reg 4 % o_y[3:0] $end
$var integer 32 & s $end
$scope module mux_inst $end
$var reg 4 ' i_data_0[3:0] $end
$var reg 4 ( i_data_1[3:0] $end
$var reg 4 ) i_data_2[3:0] $end
$var reg 4 * i_data_3[3:0] $end
$var integer 32 + s $end
$var reg 4 , o_y[3:0] $end
$upscope $end
$upscope $end
$enddefinitions $end
#0
b0010 !
b0101 "
b1010 #
b1111 $
b0010 %
b0 &
b0010 '
b0101 (
b1010 )
b1111 *
b0 +
b0010 ,
#5000000
b0101 %
b1 &
b1 +
b0101 ,
#10000000
b1010 %
b10 &
b10 +
b1010 ,
#15000000
b1111 %
b11 &
b11 +
b1111 ,
#20000000
b0101 %
b1 &
b1 +
b0101 ,
#25000000
b1010 %
b10 &
b10 +
b1010 ,
#30000000
b1111 %
b11 &
b11 +
b1111 ,
#35000000
b0101 %
b1 &
b1 +
b0101 ,
#40000000
b1010 %
b10 &
b10 +
b1010 ,
#45000000
b1111 %
b11 &
b11 +
b1111 ,
#50000000
b0101 %
b1 &
b1 +
b0101 ,
