Fibonacci-Generator/fibonacci.vhd
library IEEE;
use IEEE.std_logic_1164.all;
use IEEE.numeric_std.all;

entity fibonacci is
Port (
	clk : in std_logic;
	reset : in std_logic;
	counter : out unsigned(7 downto 0)
);
end fibonacci;

architecture rtl of fibonacci is

	signal prev_counter: unsigned(7 downto 0) := X"00";
	signal curr_counter: unsigned(7 downto 0) := X"01";

begin

	counter <= prev_counter;

	process(clk)
	begin
		if rising_edge(clk) then

			if (reset = '1') then
				prev_counter <= X"00";
				curr_counter <= X"01";
			else
				curr_counter <= curr_counter + prev_counter;
				prev_counter <= curr_counter;
			end if;

		end if;
	end process;

end rtl;

Fibonacci-Generator/fibonacci_tb.vhd
library IEEE;
use IEEE.std_logic_1164.all;
use IEEE.numeric_std.all;

entity fibonacci_tb is
end fibonacci_tb;

architecture rtl of fibonacci_tb is

	component fibonacci is
	Port (
	     clk : in std_logic;
	     reset : in std_logic;
	     counter : out unsigned(7 downto 0)
	);
	end component;

	constant CLK_PERIOD : time := 2 ns;

	signal clk: std_logic := '0';
	signal reset: std_logic := '1';
	signal counter: unsigned(7 downto 0) := X"00";

begin

	uut: fibonacci
	port map(
		clk => clk,
		reset => reset,
		counter => counter
	);

	clk_proc: process
	begin
		wait for CLK_PERIOD/2;
		clk <= not clk;
	end process;

	stim_proc: process
	begin
		wait for 5 ns;
		reset <= '0';
	end process;

end rtl;

Fibonacci-Generator/fibonacci.vcd
$date
  Thu Sep 23 14:35:16 2021
$end
$version
  GHDL v0
$end
$timescale
  1 fs
$end
$scope module standard $end
$upscope $end
$scope module std_logic_1164 $end
$upscope $end
$scope module numeric_std $end
$upscope $end
$scope module fibonacci_tb $end
$var reg 1 ! clk $end
$var reg 1 " reset $end
$var reg 8 # counter[7:0] $end
$scope module uut $end
$var reg 1 $ clk $end
$var reg 1 % reset $end
$var reg 8 & counter[7:0] $end
$var reg 8 ' prev_counter[7:0] $end
$var reg 8 ( curr_counter[7:0] $end
$upscope $end
$upscope $end
$enddefinitions $end
#0
0!
1"
b00000000 #
0$
1%
b00000000 &
b00000000 '
b00000001 (
#1000000
1!
1$
#2000000
0!
0$
#3000000
1!
1$
#4000000
0!
0$
#5000000
1!
0"
b00000001 #
1$
0%
b00000001 &
b00000001 '
#6000000
0!
0$
#7000000
1!
1$
b00000010 (
#8000000
0!
0$
#9000000
1!
b00000010 #
1$
b00000010 &
b00000010 '
b00000011 (
#10000000
0!
0$
#11000000
1!
b00000011 #
1$
b00000011 &
b00000011 '
b00000101 (
#12000000
0!
0$
#13000000
1!
b00000101 #
1$
b00000101 &
b00000101 '
b00001000 (
#14000000
0!
0$
#15000000
1!
b00001000 #
1$
b00001000 &
b00001000 '
b00001101 (
#16000000
0!
0$
#17000000
1!
b00001101 #
1$
b00001101 &
b00001101 '
b00010101 (
#18000000
0!
0$
#19000000
1!
b00010101 #
1$
b00010101 &
b00010101 '
b00100010 (
#20000000
0!
0$
#21000000
1!
b00100010 #
1$
b00100010 &
b00100010 '
b00110111 (
#22000000
0!
0$
#23000000
1!
b00110111 #
1$
b00110111 &
b00110111 '
b01011001 (
#24000000
0!
0$
#25000000
1!
b01011001 #
1$
b01011001 &
b01011001 '
b10010000 (
#26000000
0!
0$
#27000000
1!
b10010000 #
1$
b10010000 &
b10010000 '
b11101001 (
#28000000
0!
0$
#29000000
1!
b11101001 #
1$
b11101001 &
b11101001 '
b01111001 (
#30000000
0!
0$
#31000000
1!
b01111001 #
1$
b01111001 &
b01111001 '
b01100010 (
#32000000
0!
0$
#33000000
1!
b01100010 #
1$
b01100010 &
b01100010 '
b11011011 (
#34000000
0!
0$
#35000000
1!
b11011011 #
1$
b11011011 &
b11011011 '
b00111101 (
#36000000
0!
0$
#37000000
1!
b00111101 #
1$
b00111101 &
b00111101 '
b00011000 (
#38000000
0!
0$
#39000000
1!
b00011000 #
1$
b00011000 &
b00011000 '
b01010101 (
#40000000
0!
0$
#41000000
1!
b01010101 #
1$
b01010101 &
b01010101 '
b01101101 (
#42000000
0!
0$
#43000000
1!
b01101101 #
1$
b01101101 &
b01101101 '
b11000010 (
#44000000
0!
0$
#45000000
1!
b11000010 #
1$
b11000010 &
b11000010 '
b00101111 (
#46000000
0!
0$
#47000000
1!
b00101111 #
1$
b00101111 &
b00101111 '
b11110001 (
#48000000
0!
0$
#49000000
1!
b11110001 #
1$
b11110001 &
b11110001 '
b00100000 (
